youtube2srt/__init__.py
youtube2srt/youtube2srt.py
youtube2srt-0.0.2.dist-info/LICENSE
youtube2srt-0.0.2.dist-info/METADATA
youtube2srt-0.0.2.dist-info/WHEEL
youtube2srt-0.0.2.dist-info/top_level.txt
youtube2srt-0.0.2.dist-info/RECORD
