Metadata-Version: 2.1
Name: youtube2srt
Version: 0.0.2
Summary: Generates high-quality subtitles in SRT format for YouTube videos using openai-whisper by processing the audio content. Provides an option to translate the generated subtitles into English.
Author-email: Arda Akdere <ardaakdere@gmail.com>
Classifier: Programming Language :: Python :: 3
Classifier: License :: OSI Approved :: MIT License
Classifier: Operating System :: OS Independent
Classifier: Topic :: Multimedia :: Video
Classifier: Topic :: Multimedia :: Sound/Audio :: Speech
Requires-Python: >=3.7
License-File: LICENSE
Requires-Dist: yt-dlp
Requires-Dist: openai-whisper
